{
  "type": "create:sequenced_assembly",
  "ingredient": {
    "item": "kubejs:livingrock_spring"
  },
  "transitionalItem": {
    "item": "kubejs:livingrock_spring_slab"
  },
  "sequence": [
    {
      "type": "create:pressing",
      "ingredients": [{"item": "kubejs:livingrock_spring"}],
      "results": [{"item": "kubejs:livingrock_spring_slab"}]
    },
    {
      "type": "create:deploying",
      "ingredients": [
        {"item": "kubejs:livingrock_spring_slab"},
        {"item": "kubejs:rune_mold_alt"}
      ],
      "results": [
        {"item": "botania:rune_spring"}
      ],"keepHeldItem": true
    }
  ],
  "results": [
    {
      "item": "botania:rune_spring",
      "count": 1,
      "chance": 1.0
    }
  ],
  "loops": 1
}